yamdgen/__init__.py
yamdgen/yamd_helpers_function.py
yamdgen/yamdgen.py
yamdgen-0.1.1.dist-info/LICENSE
yamdgen-0.1.1.dist-info/METADATA
yamdgen-0.1.1.dist-info/WHEEL
yamdgen-0.1.1.dist-info/entry_points.txt
yamdgen-0.1.1.dist-info/top_level.txt
yamdgen-0.1.1.dist-info/RECORD
