Metadata-Version: 2.1
Name: yamdgen
Version: 0.1.1
Summary: For generating dbt yaml and md files
Home-page: https://github.com/Muizzkolapo/yamdgenerator
Author: Muizz Lateef
Author-email: lateefmuizz@gmail.com
License: UNKNOWN
Platform: UNKNOWN
Classifier: Programming Language :: Python :: 3
Classifier: License :: OSI Approved :: MIT License
Classifier: Operating System :: OS Independent
License-File: LICENSE
